roadrage/__init__.py
roadrage/main.py
roadrage/tracker.py
roadrash/__init__.py
roadrash/main.py
roadrash/tracker.py
roadrage-0.1.1.dist-info/METADATA
roadrage-0.1.1.dist-info/WHEEL
roadrage-0.1.1.dist-info/entry_points.txt
roadrage-0.1.1.dist-info/top_level.txt
roadrage-0.1.1.dist-info/RECORD
